profile_zoominfo_graphql_imp_local/ZoomInfo.py
profile_zoominfo_graphql_imp_local/__init__.py
profile_zoominfo_graphql_imp_local/constants_zoominfo.py
profile_zoominfo_graphql_imp_local-0.0.18.dist-info/METADATA
profile_zoominfo_graphql_imp_local-0.0.18.dist-info/WHEEL
profile_zoominfo_graphql_imp_local-0.0.18.dist-info/top_level.txt
profile_zoominfo_graphql_imp_local-0.0.18.dist-info/RECORD
